{
	"name": "tdt_exportRehandle",
	"properties": {
		"activities": [
			{
				"name": "Rehandle_ufv_tdt",
				"type": "ExecuteDataFlow",
				"dependsOn": [
					{
						"activity": "Rehandle_export_tdt",
						"dependencyConditions": [
							"Succeeded"
						]
					}
				],
				"policy": {
					"timeout": "0.12:00:00",
					"retry": 0,
					"retryIntervalInSeconds": 30,
					"secureOutput": false,
					"secureInput": false
				},
				"userProperties": [],
				"typeProperties": {
					"dataflow": {
						"referenceName": "Rehandle_ufv_tdt",
						"type": "DataFlowReference",
						"parameters": {
							"customer": "'tdt'"
						}
					},
					"compute": {
						"coreCount": 8,
						"computeType": "General"
					},
					"traceLevel": "Fine"
				}
			},
			{
				"name": "Rehandle_export_tdt",
				"type": "ExecuteDataFlow",
				"dependsOn": [],
				"policy": {
					"timeout": "0.12:00:00",
					"retry": 0,
					"retryIntervalInSeconds": 30,
					"secureOutput": false,
					"secureInput": false
				},
				"userProperties": [],
				"typeProperties": {
					"dataflow": {
						"referenceName": "Rehandle_export_tdt",
						"type": "DataFlowReference",
						"parameters": {
							"customer": "'tdt'"
						}
					},
					"compute": {
						"coreCount": 8,
						"computeType": "General"
					},
					"traceLevel": "Fine"
				}
			}
		],
		"annotations": []
	}
}